MANIFEST.in
README.md
pyproject.toml
setup.cfg
setup.py
django_reinstallation_app/__init__.py
django_reinstallation_app/app_tool.py
django_reinstallation_app/db_tool.py
django_reinstallation_app/installer_tool.py
django_reinstallation_app/migration_tool.py
django_reinstallation_app/print_tool.py
django_reinstallation_app.egg-info/PKG-INFO
django_reinstallation_app.egg-info/SOURCES.txt
django_reinstallation_app.egg-info/dependency_links.txt
django_reinstallation_app.egg-info/requires.txt
django_reinstallation_app.egg-info/top_level.txt
django_reinstallation_app/management/__init__.py
django_reinstallation_app/management/commands/__init__.py
django_reinstallation_app/management/commands/install.py
django_reinstallation_app/services/__init__.py
django_reinstallation_app/services/singletone.py
django_reinstallation_app/services/tools_initializers.py