Metadata-Version: 2.1
Name: django-reinstallation-app
Version: 1.0.4
Summary: App to reinstall postgres db and app migrations.
Home-page: https://github.com/Rwwwrl/database_installer
Author: Alexey Sosov
Author-email: lesh.solowiew@yandex.ru
License: BSD-3-Clause
Platform: UNKNOWN
Classifier: Environment :: Web Environment
Classifier: Framework :: Django
Classifier: Framework :: Django :: 3.0
Classifier: Framework :: Django :: 4.0
Classifier: Intended Audience :: Developers
Classifier: License :: OSI Approved :: BSD License
Classifier: Operating System :: OS Independent
Classifier: Programming Language :: Python :: 3.7
Classifier: Programming Language :: Python :: 3.8
Classifier: Programming Language :: Python :: 3.9
Classifier: Programming Language :: Python :: 3.10
Requires-Python: >=3.7
